cloudpits/__init__.py
cloudpits/instance_operations.py
cloudpits/pseudo_instance_operations.py
cloudpits/rds_config.py
cloudpits/rds_operations.py
cloudpits/save_interpols.py
cloudpits/save_performance.py
cloudpits-0.0.1.data/scripts/cloudpits_create_ondemand_jm
cloudpits-0.0.1.data/scripts/cloudpits_simulation
cloudpits-0.0.1.data/scripts/cloudpits_to_execute
cloudpits-0.0.1.dist-info/LICENSE
cloudpits-0.0.1.dist-info/METADATA
cloudpits-0.0.1.dist-info/WHEEL
cloudpits-0.0.1.dist-info/top_level.txt
cloudpits-0.0.1.dist-info/RECORD
