Metadata-Version: 2.1
Name: cloudpits
Version: 0.0.1
Summary: An AWS spot orchestrator for SPITZ enabled programs
Home-page: https://github.com/hpg-cepetro/CloudPITS
Author: Caian Benedicto
Author-email: caian@ggaunicamp.com
License: UNKNOWN
Platform: UNKNOWN
Classifier: Programming Language :: Python
Classifier: License :: OSI Approved :: MIT License
Classifier: Operating System :: OS Independent
Requires-Python: >=2.6
Requires-Dist: boto3
Requires-Dist: pymysql
